{
  "kind": "ComponentSpec",
  "metadata": {
    "id": "segmented-control",
    "name": "Segmented Control"
  },
  "data": {
    "base": {
      "enabled": {
        "root": {
          "padding": "$unit.s1",
          "cornerRadius": "$radius.full",
          "color": "$color.bg.neutral-weak"
        },
        "segment": {
          "height": "$unit.s8",
          "cornerRadius": "$radius.full",
          "paddingX": "$unit.s4",
          "minWidth": "86px",
          "fontSize": "$font-size.s5",
          "lineHeight": "$line-height.s5",
          "fontWeight": "$font-weight.medium",
          "color": "$color.fg.neutral-muted"
        },
        "indicator": {
          "cornerRadius": "$radius.full",
          "color": "$color.bg.layer-default",
          "shadow": {
            "type": "shadow",
            "value": [
              {
                "offsetX": "0px",
                "offsetY": "1px",
                "blur": "6px",
                "spread": "0px",
                "color": "#0000000d"
              }
            ]
          }
        }
      },
      "enabled,pressed": {
        "segment": {
          "color": "$color.bg.neutral-weak-pressed"
        }
      },
      "selected": {
        "segment": {
          "fontWeight": "$font-weight.bold"
        }
      },
      "enabled,selected": {
        "segment": {
          "color": "$color.fg.neutral"
        }
      },
      "enabled,selected,pressed": {
        "indicator": {
          "color": "$color.bg.layer-default-pressed"
        }
      },
      "disabled": {
        "segment": {
          "color": "$color.fg.disabled"
        }
      }
    }
  }
}